<?xml version="1.0" encoding="UTF-8"?>
<files psalm-version="4.22.0@fc2c6ab4d5fa5d644d8617089f012f3bb84b8703">
  <file src="src/BabDevSyliusProductSamplesPlugin.php">
    <MixedInferredReturnType occurrences="1">
      <code>?ExtensionInterface</code>
    </MixedInferredReturnType>
    <MixedReturnStatement occurrences="1">
      <code>$this-&gt;extension ?: null</code>
    </MixedReturnStatement>
  </file>
  <file src="src/EventListener/ProductListener.php">
    <ArgumentTypeCoercion occurrences="1">
      <code>$channel</code>
    </ArgumentTypeCoercion>
    <PossiblyNullReference occurrences="1">
      <code>getCode</code>
    </PossiblyNullReference>
  </file>
  <file src="src/Form/Extension/ProductVariantTypeExtension.php">
    <PossiblyNullArgument occurrences="1">
      <code>$variant-&gt;getProduct()</code>
    </PossiblyNullArgument>
    <PossiblyNullReference occurrences="1">
      <code>addVariant</code>
    </PossiblyNullReference>
    <UndefinedInterfaceMethod occurrences="1">
      <code>setSampleOf</code>
    </UndefinedInterfaceMethod>
  </file>
  <file src="src/Form/Type/SampleProductVariantType.php">
    <MixedAssignment occurrences="1">
      <code>$productVariant</code>
    </MixedAssignment>
    <PossiblyNullReference occurrences="3">
      <code>getData</code>
      <code>getParent</code>
      <code>getSamplesActive</code>
    </PossiblyNullReference>
    <UndefinedInterfaceMethod occurrences="1">
      <code>getSamplesActive</code>
    </UndefinedInterfaceMethod>
  </file>
</files>
